{
  "file": "1782734522563_correct-blow-far.wav",
  "featuresFile": "1782734522563_correct-blow-far.features.csv",
  "label": "correct-blow-far",
  "startedAtMillis": 1782734522563,
  "manufacturer": "Sony",
  "model": "XQ-ES54",
  "device": "XQ-ES54",
  "sdk": 35,
  "sampleRate": 16000,
  "durationSeconds": 2.000,
  "featureFrameCount": 100,
  "detector": {
    "triggered": false,
    "confidence": 0.006687,
    "speechConfidence": 0.000000,
    "noiseFloor": 0.000600,
    "reason": "ambient",
    "rms": 0.000050,
    "peak": 0.000153,
    "zeroCrossingRate": 0.362500,
    "spectralCentroid": 934.060364,
    "spectralFlatness": 0.742320,
    "frameEnergy": 0.000001,
    "spectralTemplateScore": 0.112941,
    "clipping": false
  }
}
